CHANGELOG.txt
README.txt
setup.py
PLManfred/__init__.py
PLManfred/audio.py
PLManfred/czy.py
PLManfred/logo.py
PLManfred/pogoda.py
PLManfred/say.py
PLManfred/skript.py
PLManfred.egg-info/PKG-INFO
PLManfred.egg-info/SOURCES.txt
PLManfred.egg-info/dependency_links.txt
PLManfred.egg-info/top_level.txt